blokus_gym/__init__.py
blokus_gym/envs/__init__.py
blokus_gym/envs/blokus_env.py
blokus_gym/envs/blokus_envs.py
blokus_gym/envs/game/__init__.py
blokus_gym/envs/game/blokus_game.py
blokus_gym/envs/game/board.py
blokus_gym/envs/players/__init__.py
blokus_gym/envs/players/ai_player.py
blokus_gym/envs/players/greedy_player.py
blokus_gym/envs/players/minimax_player.py
blokus_gym/envs/players/player.py
blokus_gym/envs/players/random_player.py
blokus_gym/envs/players/user_player.py
blokus_gym/envs/shapes/__init__.py
blokus_gym/envs/shapes/shape.py
blokus_gym/envs/shapes/shapes.py
rainbow/__init__.py
rainbow/agent.py
rainbow/automated_training.py
rainbow/memory_replay.py
rainbow/models.py
rainbow/segment_tree.py
rainbow/test_model.py
blokus_gym-2.2.dist-info/LICENSE
blokus_gym-2.2.dist-info/LICENSE.txt
blokus_gym-2.2.dist-info/METADATA
blokus_gym-2.2.dist-info/WHEEL
blokus_gym-2.2.dist-info/top_level.txt
blokus_gym-2.2.dist-info/RECORD
